{
  "success": true,
  "timestamp": "2025-01-22T20:05:54.398Z",
  "path": "/api/overview?dateRange=14d",
  "data": {
    "metrics": {
      "totalReviews": {
        "count": 344,
        "change": 27,
        "changeType": "decrease",
        "comparisonPeriod": "VS 14D"
      },
      "allProperties": {
        "count": 8,
        "change": 0,
        "changeType": "increase",
        "comparisonPeriod": "VS 14D"
      }
    },
    "recentReviews": [
      {
        "id": 634,
        "propertyImageSrc": "https://images.unsplash.com/photo-1560448204-e02f11c3d0e2?w=800&h=600&fit=crop&crop=center",
        "reviewTitle": "Good accommodation",
        "propertyType": "Tower Bridge View",
        "propertyLocation": "London",
        "reviewCity": "LONDON",
        "stayDuration": "7 day stay",
        "rating": "3.00",
        "publicReviewText": "Standard accommodation, met expectations.",
        "submittedAt": "2025-09-21 21:34:40",
        "guestName": "Sophie Mason",
        "channel": "marriott"
      },
      {
        "id": 635,
        "propertyImageSrc": "https://images.unsplash.com/photo-1560448204-e02f11c3d0e2?w=800&h=600&fit=crop&crop=center",
        "reviewTitle": "Excellent stay",
        "propertyType": "Modern Apartment",
        "propertyLocation": "Paris",
        "reviewCity": "PARIS",
        "stayDuration": "5 day stay",
        "rating": "4.50",
        "publicReviewText": "Amazing location and very clean. Would definitely stay again!",
        "submittedAt": "2025-09-20 18:22:15",
        "guestName": "John Smith",
        "channel": "booking"
      },
      {
        "id": 636,
        "propertyImageSrc": "https://images.unsplash.com/photo-1560448204-e02f11c3d0e2?w=800&h=600&fit=crop&crop=center",
        "reviewTitle": "Perfect location",
        "propertyType": "City Center Loft",
        "propertyLocation": "Lisbon",
        "reviewCity": "LISBON",
        "stayDuration": "3 day stay",
        "rating": "4.80",
        "publicReviewText": "Great views and walking distance to everything. Highly recommended.",
        "submittedAt": "2025-09-19 14:45:30",
        "guestName": "Maria Garcia",
        "channel": "airbnb"
      },
      {
        "id": 637,
        "propertyImageSrc": "https://images.unsplash.com/photo-1560448204-e02f11c3d0e2?w=800&h=600&fit=crop&crop=center",
        "reviewTitle": "Could be better",
        "propertyType": "Budget Studio",
        "propertyLocation": "Berlin",
        "reviewCity": "BERLIN",
        "stayDuration": "2 day stay",
        "rating": "2.50",
        "publicReviewText": "Basic accommodation, some issues with cleanliness.",
        "submittedAt": "2025-09-18 12:30:45",
        "guestName": "Alex Johnson",
        "channel": "booking"
      }
    ],
    "topRatedProperties": [
      {
        "id": "66f1abc1234567890abc1001",
        "propertyImageSrc": "https://images.unsplash.com/photo-1566073771259-6a8506099945?w=800&h=600&fit=crop&crop=center",
        "propertyName": "Louvre Loft",
        "propertyLocation": "Paris",
        "averageRating": "3.94",
        "numberOfReviews": 50,
        "totalReviews": 1240
      },
      {
        "id": "66f1abc1234567890abc1002",
        "propertyImageSrc": "https://images.unsplash.com/photo-1560448204-e02f11c3d0e2?w=800&h=600&fit=crop&crop=center",
        "propertyName": "Tower Bridge View",
        "propertyLocation": "London",
        "averageRating": "3.85",
        "numberOfReviews": 45,
        "totalReviews": 980
      },
      {
        "id": "66f1abc1234567890abc1003",
        "propertyImageSrc": "https://images.unsplash.com/photo-1560448204-e02f11c3d0e2?w=800&h=600&fit=crop&crop=center",
        "propertyName": "Alfama Charm",
        "propertyLocation": "Lisbon",
        "averageRating": "3.78",
        "numberOfReviews": 38,
        "totalReviews": 756
      },
      {
        "id": "66f1abc1234567890abc1004",
        "propertyImageSrc": "https://images.unsplash.com/photo-1560448204-e02f11c3d0e2?w=800&h=600&fit=crop&crop=center",
        "propertyName": "Modern Studio",
        "propertyLocation": "Berlin",
        "averageRating": "3.65",
        "numberOfReviews": 42,
        "totalReviews": 892
      }
    ],
    "below3StarProperties": [
      {
        "id": "66f1abc1234567890abc2001",
        "propertyImageSrc": "https://images.unsplash.com/photo-1560448204-e02f11c3d0e2?w=800&h=600&fit=crop&crop=center",
        "propertyName": "Budget Studio",
        "propertyLocation": "Berlin",
        "averageRating": "2.50",
        "numberOfReviews": 15,
        "totalReviews": 234
      },
      {
        "id": "66f1abc1234567890abc2002",
        "propertyImageSrc": "https://images.unsplash.com/photo-1560448204-e02f11c3d0e2?w=800&h=600&fit=crop&crop=center",
        "propertyName": "Old Apartment",
        "propertyLocation": "Madrid",
        "averageRating": "2.20",
        "numberOfReviews": 8,
        "totalReviews": 156
      }
    ],
    "reviewsChart": {
      "monthlyData": [
        {
          "month": "J",
          "greatReviewsCount": 150,
          "neutralReviewsCount": 350,
          "badReviewsCount": 200
        },
        {
          "month": "F",
          "greatReviewsCount": 280,
          "neutralReviewsCount": 300,
          "badReviewsCount": 150
        },
        {
          "month": "M",
          "greatReviewsCount": 450,
          "neutralReviewsCount": 280,
          "badReviewsCount": 120
        },
        {
          "month": "A",
          "greatReviewsCount": 680,
          "neutralReviewsCount": 320,
          "badReviewsCount": 180
        },
        {
          "month": "M",
          "greatReviewsCount": 580,
          "neutralReviewsCount": 400,
          "badReviewsCount": 250
        },
        {
          "month": "J",
          "greatReviewsCount": 720,
          "neutralReviewsCount": 380,
          "badReviewsCount": 200
        },
        {
          "month": "J",
          "greatReviewsCount": 650,
          "neutralReviewsCount": 420,
          "badReviewsCount": 280
        },
        {
          "month": "A",
          "greatReviewsCount": 800,
          "neutralReviewsCount": 350,
          "badReviewsCount": 150
        },
        {
          "month": "S",
          "greatReviewsCount": 750,
          "neutralReviewsCount": 300,
          "badReviewsCount": 200
        },
        {
          "month": "O",
          "greatReviewsCount": 680,
          "neutralReviewsCount": 380,
          "badReviewsCount": 320
        },
        {
          "month": "N",
          "greatReviewsCount": 620,
          "neutralReviewsCount": 420,
          "badReviewsCount": 280
        },
        {
          "month": "D",
          "greatReviewsCount": 580,
          "neutralReviewsCount": 480,
          "badReviewsCount": 350
        }
      ],
      "summary": {
        "text": "Mixed review sentiment over the last 3 months for properties in London",
        "location": "London",
        "period": "last 3 months"
      }
    },
    "guestMentions": {
      "categories": [
        "Cleanliness",
        "Lack of cleanliness", 
        "Noise complaints",
        "Maintenance problems"
      ],
      "selectedCategory": "Cleanliness",
      "locationData": [
        {
          "location": "Paris",
          "count": 15
        },
        {
          "location": "London",
          "count": 12
        },
        {
          "location": "Lisbon",
          "count": 8
        },
        {
          "location": "Berlin",
          "count": 6
        }
      ]
    }
  }
}
